<annotation>
	<folder>nevus</folder>
	<filename>ISIC_0497873.jpg</filename>
	<path>C:\Users\deSni\.deeplearning4j\data\melanomaChallenge\resized\trainSorted\nevus\ISIC_0497873.jpg</path>
	<source>
		<database>Unknown</database>
	</source>
	<size>
		<width>341</width>
		<height>256</height>
		<depth>3</depth>
	</size>
	<segmented>0</segmented>
	<object>
		<name>nevus</name>
		<pose>Unspecified</pose>
		<truncated>0</truncated>
		<difficult>0</difficult>
		<bndbox>
			<xmin>91</xmin>
			<ymin>44</ymin>
			<xmax>258</xmax>
			<ymax>189</ymax>
		</bndbox>
	</object>
	<object>
		<name>nevus</name>
		<pose>Unspecified</pose>
		<truncated>0</truncated>
		<difficult>0</difficult>
		<bndbox>
			<xmin>66</xmin>
			<ymin>198</ymin>
			<xmax>122</xmax>
			<ymax>242</ymax>
		</bndbox>
	</object>
</annotation>
