<annotation>
	<folder>melanoma</folder>
	<filename>ISIC_0217267.jpg</filename>
	<path>C:\Users\deSni\.deeplearning4j\data\melanomaChallenge\resized\trainSorted\melanoma\ISIC_0217267.jpg</path>
	<source>
		<database>Unknown</database>
	</source>
	<size>
		<width>455</width>
		<height>256</height>
		<depth>3</depth>
	</size>
	<segmented>0</segmented>
	<object>
		<name>melanoma</name>
		<pose>Unspecified</pose>
		<truncated>0</truncated>
		<difficult>0</difficult>
		<bndbox>
			<xmin>155</xmin>
			<ymin>54</ymin>
			<xmax>292</xmax>
			<ymax>225</ymax>
		</bndbox>
	</object>
	<object>
		<name>melanoma</name>
		<pose>Unspecified</pose>
		<truncated>1</truncated>
		<difficult>0</difficult>
		<bndbox>
			<xmin>22</xmin>
			<ymin>201</ymin>
			<xmax>99</xmax>
			<ymax>256</ymax>
		</bndbox>
	</object>
</annotation>
