<annotation>
	<folder>sebK_combinedSrc</folder>
	<filename>ISIC_0013063.jpg</filename>
	<path>C:\Users\Sweet\Desktop\New folder\sebK_combinedSrc\sebK_combinedSrc\ISIC_0013063.jpg</path>
	<source>
		<database>Unknown</database>
	</source>
	<size>
		<width>382</width>
		<height>256</height>
		<depth>3</depth>
	</size>
	<segmented>0</segmented>
	<object>
		<name>seborrheic keratosis</name>
		<pose>Unspecified</pose>
		<truncated>0</truncated>
		<difficult>0</difficult>
		<bndbox>
			<xmin>54</xmin>
			<ymin>10</ymin>
			<xmax>259</xmax>
			<ymax>183</ymax>
		</bndbox>
	</object>
</annotation>
