<annotation>
	<folder>melanoma</folder>
	<filename>ISIC_0237721.jpg</filename>
	<path>C:\Users\deSni\.deeplearning4j\data\melanomaChallenge\resized\trainSorted\melanoma\ISIC_0237721.jpg</path>
	<source>
		<database>Unknown</database>
	</source>
	<size>
		<width>384</width>
		<height>256</height>
		<depth>3</depth>
	</size>
	<segmented>0</segmented>
	<object>
		<name>melanoma</name>
		<pose>Unspecified</pose>
		<truncated>0</truncated>
		<difficult>0</difficult>
		<bndbox>
			<xmin>159</xmin>
			<ymin>101</ymin>
			<xmax>258</xmax>
			<ymax>172</ymax>
		</bndbox>
	</object>
	<object>
		<name>melanoma</name>
		<pose>Unspecified</pose>
		<truncated>0</truncated>
		<difficult>0</difficult>
		<bndbox>
			<xmin>293</xmin>
			<ymin>37</ymin>
			<xmax>324</xmax>
			<ymax>80</ymax>
		</bndbox>
	</object>
</annotation>
