<annotation>
	<folder>sebK_combinedSrc</folder>
	<filename>seborrheic_keratoses_2_high.jpg</filename>
	<path>C:\Users\Sweet\Desktop\New folder\sebK_combinedSrc\sebK_combinedSrc\seborrheic_keratoses_2_high.jpg</path>
	<source>
		<database>Unknown</database>
	</source>
	<size>
		<width>341</width>
		<height>256</height>
		<depth>3</depth>
	</size>
	<segmented>0</segmented>
	<object>
		<name>seborrheic keratosis</name>
		<pose>Unspecified</pose>
		<truncated>0</truncated>
		<difficult>0</difficult>
		<bndbox>
			<xmin>26</xmin>
			<ymin>20</ymin>
			<xmax>315</xmax>
			<ymax>222</ymax>
		</bndbox>
	</object>
</annotation>
